mlenvdoctor/__init__.py
mlenvdoctor/cli.py
mlenvdoctor/diagnose.py
mlenvdoctor/dockerize.py
mlenvdoctor/fix.py
mlenvdoctor/gpu.py
mlenvdoctor/utils.py
mlenvdoctor-0.1.1.dist-info/METADATA
mlenvdoctor-0.1.1.dist-info/WHEEL
mlenvdoctor-0.1.1.dist-info/entry_points.txt
mlenvdoctor-0.1.1.dist-info/licenses/LICENSE
mlenvdoctor-0.1.1.dist-info/RECORD
