Metadata-Version: 2.4
Name: mlenvdoctor
Version: 0.1.1
Summary: Diagnose & fix ML environments for LLM fine-tuning
Author: ML Environment Doctor Contributors
License: MIT
License-File: LICENSE
Keywords: cuda,diagnostics,fine-tuning,llm,machine-learning,pytorch
Classifier: Development Status :: 4 - Beta
Classifier: Intended Audience :: Developers
Classifier: License :: OSI Approved :: MIT License
Classifier: Programming Language :: Python :: 3
Classifier: Programming Language :: Python :: 3.8
Classifier: Programming Language :: Python :: 3.9
Classifier: Programming Language :: Python :: 3.10
Classifier: Programming Language :: Python :: 3.11
Classifier: Topic :: Scientific/Engineering :: Artificial Intelligence
Classifier: Topic :: Software Development :: Libraries :: Python Modules
Requires-Python: >=3.8
Requires-Dist: packaging>=23.0
Requires-Dist: psutil>=5.9.0
Requires-Dist: rich>=13.0.0
Requires-Dist: typer>=0.9.0
Provides-Extra: dev
Requires-Dist: black>=23.0.0; extra == 'dev'
Requires-Dist: mypy>=1.0.0; extra == 'dev'
Requires-Dist: pre-commit>=3.0.0; extra == 'dev'
Requires-Dist: pytest-cov>=4.0.0; extra == 'dev'
Requires-Dist: pytest>=7.0.0; extra == 'dev'
Requires-Dist: ruff>=0.1.0; extra == 'dev'
